owologs/__init__.py
owologs/processor.py
owologs-1.5.dist-info/LICENSE
owologs-1.5.dist-info/METADATA
owologs-1.5.dist-info/WHEEL
owologs-1.5.dist-info/top_level.txt
owologs-1.5.dist-info/RECORD
