Metadata-Version: 2.1
Name: owologs
Version: 1.5
License-File: LICENSE
Requires-Dist: discord.py >=2.0.0
Requires-Dist: discord >=2.0.0
Requires-Dist: colorama
